wangdiantong/__init__.py
wangdiantong/settings.py
wangdiantong/utils.py
wangdiantong/api/__init__.py
wangdiantong/api/base.py
wangdiantong/api/goods.py
wangdiantong/api/logistics.py
wangdiantong/api/order.py
wangdiantong/api/stocks.py
wangdiantong/client/__init__.py
wangdiantong/client/base.py
wangdiantong_py-0.3.0.dist-info/LICENSE
wangdiantong_py-0.3.0.dist-info/METADATA
wangdiantong_py-0.3.0.dist-info/WHEEL
wangdiantong_py-0.3.0.dist-info/top_level.txt
wangdiantong_py-0.3.0.dist-info/RECORD
